{
  "dataset_revision": "a74d7350ea12af010cfb1c21e34f1f81fd2e615b",
  "task_name": "SIB200ClusteringS2S",
  "mteb_version": "1.38.9",
  "scores": {
    "test": [
      {
        "v_measures": {
          "Level 0": [
            0.468599,
            0.446538,
            0.442869,
            0.436934,
            0.423335,
            0.424315,
            0.452594,
            0.461829,
            0.400253,
            0.460993
          ]
        },
        "v_measure": 0.441826,
        "v_measure_std": 0.020061,
        "main_score": 0.441826,
        "hf_subset": "ace_Latn",
        "languages": [
          "ace-Latn"
        ]
      },
      {
        "v_measures": {
          "Level 0": [
            0.552785,
            0.522232,
            0.537109,
            0.535626,
            0.571533,
            0.446218,
            0.463891,
            0.568061,
            0.575516,
            0.538842
          ]
        },
        "v_measure": 0.531181,
        "v_measure_std": 0.041666,
        "main_score": 0.531181,
        "hf_subset": "acm_Arab",
        "languages": [
          "acm-Arab"
        ]
      },
      {
        "v_measures": {
          "Level 0": [
            0.536052,
            0.549987,
            0.477828,
            0.49576,
            0.546217,
            0.540341,
            0.531656,
            0.555404,
            0.489112,
            0.51429
          ]
        },
        "v_measure": 0.523665,
        "v_measure_std": 0.026203,
        "main_score": 0.523665,
        "hf_subset": "acq_Arab",
        "languages": [
          "acq-Arab"
        ]
      },
      {
        "v_measures": {
          "Level 0": [
            0.513657,
            0.496592,
            0.5252,
            0.580933,
            0.494262,
            0.484659,
            0.518197,
            0.48502,
            0.578854,
            0.496966
          ]
        },
        "v_measure": 0.517434,
        "v_measure_std": 0.033756,
        "main_score": 0.517434,
        "hf_subset": "aeb_Arab",
        "languages": [
          "aeb-Arab"
        ]
      },
      {
        "v_measures": {
          "Level 0": [
            0.565892,
            0.53593,
            0.618708,
            0.575545,
            0.642094,
            0.48851,
            0.591715,
            0.542467,
            0.59446,
            0.600239
          ]
        },
        "v_measure": 0.575556,
        "v_measure_std": 0.042252,
        "main_score": 0.575556,
        "hf_subset": "afr_Latn",
        "languages": [
          "afr-Latn"
        ]
      },
      {
        "v_measures": {
          "Level 0": [
            0.493052,
            0.556285,
            0.491084,
            0.559025,
            0.497119,
            0.602085,
            0.569974,
            0.473197,
            0.585546,
            0.437869
          ]
        },
        "v_measure": 0.526523,
        "v_measure_std": 0.05193,
        "main_score": 0.526523,
        "hf_subset": "ajp_Arab",
        "languages": [
          "ajp-Arab"
        ]
      },
      {
        "v_measures": {
          "Level 0": [
            0.324165,
            0.318958,
            0.351831,
            0.281351,
            0.356469,
            0.312647,
            0.332092,
            0.328188,
            0.255435,
            0.345547
          ]
        },
        "v_measure": 0.320668,
        "v_measure_std": 0.029899,
        "main_score": 0.320668,
        "hf_subset": "aka_Latn",
        "languages": [
          "aka-Latn"
        ]
      },
      {
        "v_measures": {
          "Level 0": [
            0.541627,
            0.537849,
            0.576717,
            0.585705,
            0.493279,
            0.60696,
            0.551881,
            0.579319,
            0.481705,
            0.613447
          ]
        },
        "v_measure": 0.556849,
        "v_measure_std": 0.042133,
        "main_score": 0.556849,
        "hf_subset": "als_Latn",
        "languages": [
          "als-Latn"
        ]
      },
      {
        "v_measures": {
          "Level 0": [
            0.431034,
            0.476695,
            0.38681,
            0.397806,
            0.437237,
            0.40423,
            0.379393,
            0.394544,
            0.377421,
            0.352945
          ]
        },
        "v_measure": 0.403812,
        "v_measure_std": 0.033855,
        "main_score": 0.403812,
        "hf_subset": "amh_Ethi",
        "languages": [
          "amh-Ethi"
        ]
      },
      {
        "v_measures": {
          "Level 0": [
            0.549536,
            0.597123,
            0.540097,
            0.491053,
            0.579685,
            0.591132,
            0.443102,
            0.545535,
            0.511423,
            0.536549
          ]
        },
        "v_measure": 0.538524,
        "v_measure_std": 0.044907,
        "main_score": 0.538524,
        "hf_subset": "apc_Arab",
        "languages": [
          "apc-Arab"
        ]
      },
      {
        "v_measures": {
          "Level 0": [
            0.344853,
            0.340252,
            0.359635,
            0.338485,
            0.355061,
            0.307115,
            0.378541,
            0.36957,
            0.341419,
            0.370129
          ]
        },
        "v_measure": 0.350506,
        "v_measure_std": 0.019712,
        "main_score": 0.350506,
        "hf_subset": "arb_Latn",
        "languages": [
          "arb-Latn"
        ]
      },
      {
        "v_measures": {
          "Level 0": [
            0.57289,
            0.570722,
            0.59689,
            0.529188,
            0.597094,
            0.530941,
            0.489808,
            0.504387,
            0.553078,
            0.507861
          ]
        },
        "v_measure": 0.545286,
        "v_measure_std": 0.036651,
        "main_score": 0.545286,
        "hf_subset": "ars_Arab",
        "languages": [
          "ars-Arab"
        ]
      },
      {
        "v_measures": {
          "Level 0": [
            0.509756,
            0.453546,
            0.549833,
            0.536695,
            0.523905,
            0.547034,
            0.579394,
            0.509795,
            0.501845,
            0.462256
          ]
        },
        "v_measure": 0.517406,
        "v_measure_std": 0.036965,
        "main_score": 0.517406,
        "hf_subset": "ary_Arab",
        "languages": [
          "ary-Arab"
        ]
      },
      {
        "v_measures": {
          "Level 0": [
            0.502958,
            0.49654,
            0.49643,
            0.530483,
            0.518748,
            0.462095,
            0.479837,
            0.549262,
            0.54299,
            0.59582
          ]
        },
        "v_measure": 0.517516,
        "v_measure_std": 0.036804,
        "main_score": 0.517516,
        "hf_subset": "arz_Arab",
        "languages": [
          "arz-Arab"
        ]
      },
      {
        "v_measures": {
          "Level 0": [
            0.454553,
            0.483213,
            0.505722,
            0.442899,
            0.486639,
            0.490767,
            0.518728,
            0.540349,
            0.443032,
            0.481838
          ]
        },
        "v_measure": 0.484774,
        "v_measure_std": 0.030232,
        "main_score": 0.484774,
        "hf_subset": "asm_Beng",
        "languages": [
          "asm-Beng"
        ]
      },
      {
        "v_measures": {
          "Level 0": [
            0.470397,
            0.573288,
            0.56989,
            0.587841,
            0.562712,
            0.497291,
            0.556371,
            0.558398,
            0.539016,
            0.544477
          ]
        },
        "v_measure": 0.545968,
        "v_measure_std": 0.034272,
        "main_score": 0.545968,
        "hf_subset": "ast_Latn",
        "languages": [
          "ast-Latn"
        ]
      },
      {
        "v_measures": {
          "Level 0": [
            0.549879,
            0.509392,
            0.545786,
            0.500287,
            0.512915,
            0.46844,
            0.477245,
            0.463631,
            0.542706,
            0.557496
          ]
        },
        "v_measure": 0.512778,
        "v_measure_std": 0.033426,
        "main_score": 0.512778,
        "hf_subset": "awa_Deva",
        "languages": [
          "awa-Deva"
        ]
      },
      {
        "v_measures": {
          "Level 0": [
            0.242491,
            0.218653,
            0.265759,
            0.202215,
            0.257252,
            0.235297,
            0.236171,
            0.251862,
            0.271721,
            0.279324
          ]
        },
        "v_measure": 0.246075,
        "v_measure_std": 0.02283,
        "main_score": 0.246075,
        "hf_subset": "ayr_Latn",
        "languages": [
          "ayr-Latn"
        ]
      },
      {
        "v_measures": {
          "Level 0": [
            0.414054,
            0.400958,
            0.367111,
            0.452088,
            0.355005,
            0.527066,
            0.438723,
            0.426667,
            0.440146,
            0.45094
          ]
        },
        "v_measure": 0.427276,
        "v_measure_std": 0.045979,
        "main_score": 0.427276,
        "hf_subset": "azb_Arab",
        "languages": [
          "azb-Arab"
        ]
      },
      {
        "v_measures": {
          "Level 0": [
            0.542369,
            0.521629,
            0.524662,
            0.516861,
            0.645466,
            0.527227,
            0.54947,
            0.50831,
            0.545271,
            0.500334
          ]
        },
        "v_measure": 0.53816,
        "v_measure_std": 0.038809,
        "main_score": 0.53816,
        "hf_subset": "azj_Latn",
        "languages": [
          "azj-Latn"
        ]
      },
      {
        "v_measures": {
          "Level 0": [
            0.461434,
            0.518701,
            0.572256,
            0.520066,
            0.513584,
            0.503485,
            0.496839,
            0.557433,
            0.506362,
            0.581634
          ]
        },
        "v_measure": 0.523179,
        "v_measure_std": 0.035068,
        "main_score": 0.523179,
        "hf_subset": "bak_Cyrl",
        "languages": [
          "bak-Cyrl"
        ]
      },
      {
        "v_measures": {
          "Level 0": [
            0.200751,
            0.243769,
            0.217487,
            0.159706,
            0.229087,
            0.251127,
            0.260594,
            0.232016,
            0.218763,
            0.218926
          ]
        },
        "v_measure": 0.223223,
        "v_measure_std": 0.027055,
        "main_score": 0.223223,
        "hf_subset": "bam_Latn",
        "languages": [
          "bam-Latn"
        ]
      },
      {
        "v_measures": {
          "Level 0": [
            0.464442,
            0.446168,
            0.52003,
            0.471733,
            0.468804,
            0.466652,
            0.455685,
            0.507923,
            0.451861,
            0.513198
          ]
        },
        "v_measure": 0.47665,
        "v_measure_std": 0.025521,
        "main_score": 0.47665,
        "hf_subset": "ban_Latn",
        "languages": [
          "ban-Latn"
        ]
      },
      {
        "v_measures": {
          "Level 0": [
            0.575728,
            0.564139,
            0.575915,
            0.551701,
            0.623745,
            0.56046,
            0.646592,
            0.570952,
            0.532604,
            0.523782
          ]
        },
        "v_measure": 0.572562,
        "v_measure_std": 0.035711,
        "main_score": 0.572562,
        "hf_subset": "bel_Cyrl",
        "languages": [
          "bel-Cyrl"
        ]
      },
      {
        "v_measures": {
          "Level 0": [
            0.23645,
            0.292619,
            0.276421,
            0.349401,
            0.262405,
            0.335411,
            0.264481,
            0.334283,
            0.265633,
            0.301717
          ]
        },
        "v_measure": 0.291882,
        "v_measure_std": 0.035663,
        "main_score": 0.291882,
        "hf_subset": "bem_Latn",
        "languages": [
          "bem-Latn"
        ]
      },
      {
        "v_measures": {
          "Level 0": [
            0.520061,
            0.567875,
            0.547347,
            0.60815,
            0.576198,
            0.54615,
            0.493557,
            0.566599,
            0.577805,
            0.515651
          ]
        },
        "v_measure": 0.551939,
        "v_measure_std": 0.032684,
        "main_score": 0.551939,
        "hf_subset": "ben_Beng",
        "languages": [
          "ben-Beng"
        ]
      },
      {
        "v_measures": {
          "Level 0": [
            0.43205,
            0.478261,
            0.54934,
            0.501957,
            0.5567,
            0.505517,
            0.534191,
            0.554338,
            0.49094,
            0.473559
          ]
        },
        "v_measure": 0.507685,
        "v_measure_std": 0.03884,
        "main_score": 0.507685,
        "hf_subset": "bho_Deva",
        "languages": [
          "bho-Deva"
        ]
      },
      {
        "v_measures": {
          "Level 0": [
            0.489145,
            0.46383,
            0.468904,
            0.408837,
            0.453487,
            0.487266,
            0.516698,
            0.414341,
            0.45458,
            0.485198
          ]
        },
        "v_measure": 0.464229,
        "v_measure_std": 0.031831,
        "main_score": 0.464229,
        "hf_subset": "bjn_Latn",
        "languages": [
          "bjn-Latn"
        ]
      },
      {
        "v_measures": {
          "Level 0": [
            0.206731,
            0.229167,
            0.264246,
            0.250676,
            0.230097,
            0.24943,
            0.274953,
            0.239631,
            0.268498,
            0.263838
          ]
        },
        "v_measure": 0.247727,
        "v_measure_std": 0.020293,
        "main_score": 0.247727,
        "hf_subset": "bod_Tibt",
        "languages": [
          "bod-Tibt"
        ]
      },
      {
        "v_measures": {
          "Level 0": [
            0.509831,
            0.496785,
            0.550776,
            0.622847,
            0.51054,
            0.513036,
            0.570344,
            0.513622,
            0.534224,
            0.446965
          ]
        },
        "v_measure": 0.526897,
        "v_measure_std": 0.044655,
        "main_score": 0.526897,
        "hf_subset": "bos_Latn",
        "languages": [
          "bos-Latn"
        ]
      },
      {
        "v_measures": {
          "Level 0": [
            0.36742,
            0.351071,
            0.316206,
            0.318787,
            0.385561,
            0.285157,
            0.278981,
            0.293237,
            0.286681,
            0.37981
          ]
        },
        "v_measure": 0.326291,
        "v_measure_std": 0.039284,
        "main_score": 0.326291,
        "hf_subset": "bug_Latn",
        "languages": [
          "bug-Latn"
        ]
      },
      {
        "v_measures": {
          "Level 0": [
            0.535611,
            0.552815,
            0.532018,
            0.537459,
            0.498317,
            0.522743,
            0.481914,
            0.588313,
            0.50028,
            0.565336
          ]
        },
        "v_measure": 0.531481,
        "v_measure_std": 0.030807,
        "main_score": 0.531481,
        "hf_subset": "bul_Cyrl",
        "languages": [
          "bul-Cyrl"
        ]
      },
      {
        "v_measures": {
          "Level 0": [
            0.526671,
            0.562998,
            0.571726,
            0.528657,
            0.663566,
            0.479118,
            0.566244,
            0.489503,
            0.538211,
            0.604967
          ]
        },
        "v_measure": 0.553166,
        "v_measure_std": 0.051523,
        "main_score": 0.553166,
        "hf_subset": "cat_Latn",
        "languages": [
          "cat-Latn"
        ]
      },
      {
        "v_measures": {
          "Level 0": [
            0.485921,
            0.511703,
            0.53434,
            0.591218,
            0.525069,
            0.467167,
            0.561688,
            0.568383,
            0.489162,
            0.623972
          ]
        },
        "v_measure": 0.535862,
        "v_measure_std": 0.047591,
        "main_score": 0.535862,
        "hf_subset": "ceb_Latn",
        "languages": [
          "ceb-Latn"
        ]
      },
      {
        "v_measures": {
          "Level 0": [
            0.51269,
            0.536157,
            0.546843,
            0.543249,
            0.563309,
            0.539269,
            0.568501,
            0.589233,
            0.550201,
            0.518299
          ]
        },
        "v_measure": 0.546775,
        "v_measure_std": 0.021712,
        "main_score": 0.546775,
        "hf_subset": "ces_Latn",
        "languages": [
          "ces-Latn"
        ]
      },
      {
        "v_measures": {
          "Level 0": [
            0.21672,
            0.217711,
            0.23794,
            0.238151,
            0.23984,
            0.225294,
            0.215678,
            0.214964,
            0.231394,
            0.263654
          ]
        },
        "v_measure": 0.230135,
        "v_measure_std": 0.014633,
        "main_score": 0.230135,
        "hf_subset": "cjk_Latn",
        "languages": [
          "cjk-Latn"
        ]
      },
      {
        "v_measures": {
          "Level 0": [
            0.471799,
            0.441357,
            0.404557,
            0.456637,
            0.464323,
            0.463665,
            0.366206,
            0.482983,
            0.44418,
            0.469636
          ]
        },
        "v_measure": 0.446534,
        "v_measure_std": 0.033852,
        "main_score": 0.446534,
        "hf_subset": "ckb_Arab",
        "languages": [
          "ckb-Arab"
        ]
      },
      {
        "v_measures": {
          "Level 0": [
            0.548723,
            0.4842,
            0.507738,
            0.504712,
            0.503841,
            0.461879,
            0.513687,
            0.476964,
            0.512978,
            0.501603
          ]
        },
        "v_measure": 0.501633,
        "v_measure_std": 0.022441,
        "main_score": 0.501633,
        "hf_subset": "crh_Latn",
        "languages": [
          "crh-Latn"
        ]
      },
      {
        "v_measures": {
          "Level 0": [
            0.508832,
            0.4685,
            0.541831,
            0.46838,
            0.463306,
            0.475304,
            0.517756,
            0.46214,
            0.474226,
            0.464104
          ]
        },
        "v_measure": 0.484438,
        "v_measure_std": 0.026563,
        "main_score": 0.484438,
        "hf_subset": "cym_Latn",
        "languages": [
          "cym-Latn"
        ]
      },
      {
        "v_measures": {
          "Level 0": [
            0.558896,
            0.521264,
            0.46275,
            0.505216,
            0.559677,
            0.564197,
            0.502265,
            0.576918,
            0.583317,
            0.577243
          ]
        },
        "v_measure": 0.541174,
        "v_measure_std": 0.038594,
        "main_score": 0.541174,
        "hf_subset": "dan_Latn",
        "languages": [
          "dan-Latn"
        ]
      },
      {
        "v_measures": {
          "Level 0": [
            0.480619,
            0.55142,
            0.505269,
            0.521954,
            0.566443,
            0.509565,
            0.452498,
            0.531416,
            0.559073,
            0.468464
          ]
        },
        "v_measure": 0.514672,
        "v_measure_std": 0.036892,
        "main_score": 0.514672,
        "hf_subset": "deu_Latn",
        "languages": [
          "deu-Latn"
        ]
      },
      {
        "v_measures": {
          "Level 0": [
            0.173108,
            0.22256,
            0.236322,
            0.183654,
            0.199447,
            0.222855,
            0.22243,
            0.278746,
            0.184967,
            0.161012
          ]
        },
        "v_measure": 0.20851,
        "v_measure_std": 0.033267,
        "main_score": 0.20851,
        "hf_subset": "dik_Latn",
        "languages": [
          "dik-Latn"
        ]
      },
      {
        "v_measures": {
          "Level 0": [
            0.21299,
            0.251523,
            0.299737,
            0.207651,
            0.227,
            0.253643,
            0.258354,
            0.276383,
            0.303912,
            0.265477
          ]
        },
        "v_measure": 0.255667,
        "v_measure_std": 0.031261,
        "main_score": 0.255667,
        "hf_subset": "dyu_Latn",
        "languages": [
          "dyu-Latn"
        ]
      },
      {
        "v_measures": {
          "Level 0": [
            0.185039,
            0.169837,
            0.223306,
            0.184275,
            0.196358,
            0.190914,
            0.215467,
            0.23373,
            0.174855,
            0.16876
          ]
        },
        "v_measure": 0.194254,
        "v_measure_std": 0.021622,
        "main_score": 0.194254,
        "hf_subset": "dzo_Tibt",
        "languages": [
          "dzo-Tibt"
        ]
      },
      {
        "v_measures": {
          "Level 0": [
            0.513219,
            0.543739,
            0.474053,
            0.621017,
            0.499872,
            0.479472,
            0.538219,
            0.450471,
            0.502897,
            0.590745
          ]
        },
        "v_measure": 0.52137,
        "v_measure_std": 0.050416,
        "main_score": 0.52137,
        "hf_subset": "ell_Grek",
        "languages": [
          "ell-Grek"
        ]
      },
      {
        "v_measures": {
          "Level 0": [
            0.426012,
            0.506173,
            0.412047,
            0.420909,
            0.532056,
            0.522735,
            0.571883,
            0.53256,
            0.538396,
            0.567692
          ]
        },
        "v_measure": 0.503046,
        "v_measure_std": 0.057653,
        "main_score": 0.503046,
        "hf_subset": "eng_Latn",
        "languages": [
          "eng-Latn"
        ]
      },
      {
        "v_measures": {
          "Level 0": [
            0.573202,
            0.539726,
            0.534882,
            0.502397,
            0.509859,
            0.593989,
            0.58586,
            0.607023,
            0.598939,
            0.506642
          ]
        },
        "v_measure": 0.555252,
        "v_measure_std": 0.039015,
        "main_score": 0.555252,
        "hf_subset": "epo_Latn",
        "languages": [
          "epo-Latn"
        ]
      },
      {
        "v_measures": {
          "Level 0": [
            0.52721,
            0.582205,
            0.469499,
            0.487622,
            0.550186,
            0.521339,
            0.608889,
            0.532994,
            0.538204,
            0.620725
          ]
        },
        "v_measure": 0.543887,
        "v_measure_std": 0.046124,
        "main_score": 0.543887,
        "hf_subset": "est_Latn",
        "languages": [
          "est-Latn"
        ]
      },
      {
        "v_measures": {
          "Level 0": [
            0.521198,
            0.589592,
            0.538709,
            0.519485,
            0.528509,
            0.521683,
            0.575665,
            0.510412,
            0.499107,
            0.552156
          ]
        },
        "v_measure": 0.535652,
        "v_measure_std": 0.027352,
        "main_score": 0.535652,
        "hf_subset": "eus_Latn",
        "languages": [
          "eus-Latn"
        ]
      },
      {
        "v_measures": {
          "Level 0": [
            0.251647,
            0.246497,
            0.226908,
            0.213367,
            0.224304,
            0.243386,
            0.188304,
            0.214827,
            0.217755,
            0.245209
          ]
        },
        "v_measure": 0.22722,
        "v_measure_std": 0.018739,
        "main_score": 0.22722,
        "hf_subset": "ewe_Latn",
        "languages": [
          "ewe-Latn"
        ]
      },
      {
        "v_measures": {
          "Level 0": [
            0.382426,
            0.481665,
            0.429863,
            0.423064,
            0.438058,
            0.433859,
            0.469427,
            0.505341,
            0.46425,
            0.441473
          ]
        },
        "v_measure": 0.446943,
        "v_measure_std": 0.03275,
        "main_score": 0.446943,
        "hf_subset": "fao_Latn",
        "languages": [
          "fao-Latn"
        ]
      },
      {
        "v_measures": {
          "Level 0": [
            0.269304,
            0.196413,
            0.313443,
            0.240882,
            0.307801,
            0.288922,
            0.25651,
            0.2915,
            0.271941,
            0.281307
          ]
        },
        "v_measure": 0.271802,
        "v_measure_std": 0.032682,
        "main_score": 0.271802,
        "hf_subset": "fij_Latn",
        "languages": [
          "fij-Latn"
        ]
      },
      {
        "v_measures": {
          "Level 0": [
            0.464707,
            0.568889,
            0.60298,
            0.534627,
            0.589857,
            0.517874,
            0.564761,
            0.508284,
            0.59734,
            0.509127
          ]
        },
        "v_measure": 0.545845,
        "v_measure_std": 0.043581,
        "main_score": 0.545845,
        "hf_subset": "fin_Latn",
        "languages": [
          "fin-Latn"
        ]
      },
      {
        "v_measures": {
          "Level 0": [
            0.222254,
            0.21769,
            0.216814,
            0.217021,
            0.244417,
            0.249299,
            0.176462,
            0.242509,
            0.220356,
            0.178505
          ]
        },
        "v_measure": 0.218533,
        "v_measure_std": 0.023636,
        "main_score": 0.218533,
        "hf_subset": "fon_Latn",
        "languages": [
          "fon-Latn"
        ]
      },
      {
        "v_measures": {
          "Level 0": [
            0.555028,
            0.520795,
            0.526821,
            0.582932,
            0.458563,
            0.55282,
            0.518288,
            0.59683,
            0.52941,
            0.568641
          ]
        },
        "v_measure": 0.541013,
        "v_measure_std": 0.037458,
        "main_score": 0.541013,
        "hf_subset": "fra_Latn",
        "languages": [
          "fra-Latn"
        ]
      },
      {
        "v_measures": {
          "Level 0": [
            0.506527,
            0.474801,
            0.406978,
            0.546048,
            0.553572,
            0.450505,
            0.478789,
            0.507331,
            0.482174,
            0.457974
          ]
        },
        "v_measure": 0.48647,
        "v_measure_std": 0.041866,
        "main_score": 0.48647,
        "hf_subset": "fur_Latn",
        "languages": [
          "fur-Latn"
        ]
      },
      {
        "v_measures": {
          "Level 0": [
            0.213979,
            0.292294,
            0.224556,
            0.249436,
            0.262753,
            0.229071,
            0.283583,
            0.231259,
            0.239098,
            0.281585
          ]
        },
        "v_measure": 0.250761,
        "v_measure_std": 0.026314,
        "main_score": 0.250761,
        "hf_subset": "fuv_Latn",
        "languages": [
          "fuv-Latn"
        ]
      },
      {
        "v_measures": {
          "Level 0": [
            0.183238,
            0.235654,
            0.245276,
            0.207776,
            0.166297,
            0.192861,
            0.172555,
            0.175827,
            0.206738,
            0.195203
          ]
        },
        "v_measure": 0.198142,
        "v_measure_std": 0.024942,
        "main_score": 0.198142,
        "hf_subset": "gaz_Latn",
        "languages": [
          "gaz-Latn"
        ]
      },
      {
        "v_measures": {
          "Level 0": [
            0.381905,
            0.380567,
            0.408041,
            0.333727,
            0.343936,
            0.366731,
            0.353797,
            0.378676,
            0.384752,
            0.311545
          ]
        },
        "v_measure": 0.364368,
        "v_measure_std": 0.027132,
        "main_score": 0.364368,
        "hf_subset": "gla_Latn",
        "languages": [
          "gla-Latn"
        ]
      },
      {
        "v_measures": {
          "Level 0": [
            0.442612,
            0.430222,
            0.450581,
            0.447805,
            0.418153,
            0.471895,
            0.425032,
            0.441644,
            0.503104,
            0.470366
          ]
        },
        "v_measure": 0.450141,
        "v_measure_std": 0.024233,
        "main_score": 0.450141,
        "hf_subset": "gle_Latn",
        "languages": [
          "gle-Latn"
        ]
      },
      {
        "v_measures": {
          "Level 0": [
            0.514794,
            0.549512,
            0.511569,
            0.504183,
            0.494107,
            0.552442,
            0.607431,
            0.618299,
            0.57264,
            0.497904
          ]
        },
        "v_measure": 0.542288,
        "v_measure_std": 0.043059,
        "main_score": 0.542288,
        "hf_subset": "glg_Latn",
        "languages": [
          "glg-Latn"
        ]
      },
      {
        "v_measures": {
          "Level 0": [
            0.430579,
            0.438684,
            0.41085,
            0.373409,
            0.357527,
            0.423861,
            0.372826,
            0.455756,
            0.434172,
            0.430284
          ]
        },
        "v_measure": 0.412795,
        "v_measure_std": 0.031503,
        "main_score": 0.412795,
        "hf_subset": "grn_Latn",
        "languages": [
          "grn-Latn"
        ]
      },
      {
        "v_measures": {
          "Level 0": [
            0.48256,
            0.541213,
            0.50506,
            0.521745,
            0.548858,
            0.586434,
            0.506825,
            0.528156,
            0.566092,
            0.509226
          ]
        },
        "v_measure": 0.529617,
        "v_measure_std": 0.029799,
        "main_score": 0.529617,
        "hf_subset": "guj_Gujr",
        "languages": [
          "guj-Gujr"
        ]
      },
      {
        "v_measures": {
          "Level 0": [
            0.48993,
            0.543694,
            0.588823,
            0.554029,
            0.510971,
            0.59483,
            0.514141,
            0.46824,
            0.552201,
            0.545885
          ]
        },
        "v_measure": 0.536274,
        "v_measure_std": 0.038488,
        "main_score": 0.536274,
        "hf_subset": "hat_Latn",
        "languages": [
          "hat-Latn"
        ]
      },
      {
        "v_measures": {
          "Level 0": [
            0.432806,
            0.460952,
            0.420289,
            0.46403,
            0.417864,
            0.39196,
            0.464457,
            0.384843,
            0.433022,
            0.467357
          ]
        },
        "v_measure": 0.433758,
        "v_measure_std": 0.028814,
        "main_score": 0.433758,
        "hf_subset": "hau_Latn",
        "languages": [
          "hau-Latn"
        ]
      },
      {
        "v_measures": {
          "Level 0": [
            0.55352,
            0.48773,
            0.512841,
            0.530629,
            0.513596,
            0.530576,
            0.54789,
            0.503913,
            0.495019,
            0.518169
          ]
        },
        "v_measure": 0.519388,
        "v_measure_std": 0.020353,
        "main_score": 0.519388,
        "hf_subset": "heb_Hebr",
        "languages": [
          "heb-Hebr"
        ]
      },
      {
        "v_measures": {
          "Level 0": [
            0.537035,
            0.504015,
            0.533509,
            0.543184,
            0.570004,
            0.510465,
            0.475142,
            0.529832,
            0.532824,
            0.534208
          ]
        },
        "v_measure": 0.527022,
        "v_measure_std": 0.024164,
        "main_score": 0.527022,
        "hf_subset": "hin_Deva",
        "languages": [
          "hin-Deva"
        ]
      },
      {
        "v_measures": {
          "Level 0": [
            0.522111,
            0.443483,
            0.525208,
            0.518863,
            0.472179,
            0.430462,
            0.521201,
            0.525263,
            0.574438,
            0.467483
          ]
        },
        "v_measure": 0.500069,
        "v_measure_std": 0.042391,
        "main_score": 0.500069,
        "hf_subset": "hne_Deva",
        "languages": [
          "hne-Deva"
        ]
      },
      {
        "v_measures": {
          "Level 0": [
            0.594437,
            0.579979,
            0.574652,
            0.507131,
            0.592593,
            0.534377,
            0.543918,
            0.615092,
            0.572155,
            0.607145
          ]
        },
        "v_measure": 0.572148,
        "v_measure_std": 0.032407,
        "main_score": 0.572148,
        "hf_subset": "hrv_Latn",
        "languages": [
          "hrv-Latn"
        ]
      },
      {
        "v_measures": {
          "Level 0": [
            0.63779,
            0.614323,
            0.527448,
            0.609018,
            0.598077,
            0.577981,
            0.583706,
            0.521201,
            0.519267,
            0.575126
          ]
        },
        "v_measure": 0.576394,
        "v_measure_std": 0.039377,
        "main_score": 0.576394,
        "hf_subset": "hun_Latn",
        "languages": [
          "hun-Latn"
        ]
      },
      {
        "v_measures": {
          "Level 0": [
            0.491523,
            0.580489,
            0.504541,
            0.498463,
            0.501934,
            0.518545,
            0.474914,
            0.469747,
            0.487751,
            0.54989
          ]
        },
        "v_measure": 0.50778,
        "v_measure_std": 0.032403,
        "main_score": 0.50778,
        "hf_subset": "hye_Armn",
        "languages": [
          "hye-Armn"
        ]
      },
      {
        "v_measures": {
          "Level 0": [
            0.331965,
            0.392977,
            0.396105,
            0.358534,
            0.36592,
            0.369848,
            0.373361,
            0.375374,
            0.356869,
            0.413423
          ]
        },
        "v_measure": 0.373438,
        "v_measure_std": 0.021873,
        "main_score": 0.373438,
        "hf_subset": "ibo_Latn",
        "languages": [
          "ibo-Latn"
        ]
      },
      {
        "v_measures": {
          "Level 0": [
            0.511309,
            0.466036,
            0.477652,
            0.518721,
            0.455807,
            0.483522,
            0.452974,
            0.476384,
            0.414183,
            0.490604
          ]
        },
        "v_measure": 0.474719,
        "v_measure_std": 0.028612,
        "main_score": 0.474719,
        "hf_subset": "ilo_Latn",
        "languages": [
          "ilo-Latn"
        ]
      },
      {
        "v_measures": {
          "Level 0": [
            0.531175,
            0.483826,
            0.587656,
            0.51718,
            0.524339,
            0.546439,
            0.575231,
            0.511685,
            0.609903,
            0.553457
          ]
        },
        "v_measure": 0.544089,
        "v_measure_std": 0.036408,
        "main_score": 0.544089,
        "hf_subset": "ind_Latn",
        "languages": [
          "ind-Latn"
        ]
      },
      {
        "v_measures": {
          "Level 0": [
            0.48475,
            0.433197,
            0.505985,
            0.515039,
            0.498675,
            0.511964,
            0.501132,
            0.539531,
            0.491991,
            0.505743
          ]
        },
        "v_measure": 0.498801,
        "v_measure_std": 0.025978,
        "main_score": 0.498801,
        "hf_subset": "isl_Latn",
        "languages": [
          "isl-Latn"
        ]
      },
      {
        "v_measures": {
          "Level 0": [
            0.489387,
            0.482178,
            0.562366,
            0.496113,
            0.574037,
            0.562338,
            0.467094,
            0.508662,
            0.520663,
            0.501125
          ]
        },
        "v_measure": 0.516396,
        "v_measure_std": 0.035497,
        "main_score": 0.516396,
        "hf_subset": "ita_Latn",
        "languages": [
          "ita-Latn"
        ]
      },
      {
        "v_measures": {
          "Level 0": [
            0.515323,
            0.512011,
            0.580587,
            0.485779,
            0.512586,
            0.469608,
            0.505819,
            0.493119,
            0.466061,
            0.475045
          ]
        },
        "v_measure": 0.501594,
        "v_measure_std": 0.031604,
        "main_score": 0.501594,
        "hf_subset": "jav_Latn",
        "languages": [
          "jav-Latn"
        ]
      },
      {
        "v_measures": {
          "Level 0": [
            0.551202,
            0.495708,
            0.496313,
            0.508505,
            0.544461,
            0.551039,
            0.458332,
            0.543178,
            0.513137,
            0.517258
          ]
        },
        "v_measure": 0.517913,
        "v_measure_std": 0.028583,
        "main_score": 0.517913,
        "hf_subset": "jpn_Jpan",
        "languages": [
          "jpn-Jpan"
        ]
      },
      {
        "v_measures": {
          "Level 0": [
            0.116106,
            0.133722,
            0.129934,
            0.121613,
            0.127418,
            0.112161,
            0.13575,
            0.122303,
            0.145205,
            0.141679
          ]
        },
        "v_measure": 0.128589,
        "v_measure_std": 0.010208,
        "main_score": 0.128589,
        "hf_subset": "kab_Latn",
        "languages": [
          "kab-Latn"
        ]
      },
      {
        "v_measures": {
          "Level 0": [
            0.24965,
            0.226724,
            0.259289,
            0.301847,
            0.235797,
            0.218103,
            0.234156,
            0.221726,
            0.21074,
            0.191953
          ]
        },
        "v_measure": 0.234998,
        "v_measure_std": 0.028716,
        "main_score": 0.234998,
        "hf_subset": "kac_Latn",
        "languages": [
          "kac-Latn"
        ]
      },
      {
        "v_measures": {
          "Level 0": [
            0.26616,
            0.295363,
            0.245219,
            0.256408,
            0.198323,
            0.247016,
            0.247677,
            0.228062,
            0.224471,
            0.218275
          ]
        },
        "v_measure": 0.242697,
        "v_measure_std": 0.025834,
        "main_score": 0.242697,
        "hf_subset": "kam_Latn",
        "languages": [
          "kam-Latn"
        ]
      },
      {
        "v_measures": {
          "Level 0": [
            0.523088,
            0.525829,
            0.531577,
            0.547705,
            0.514783,
            0.456262,
            0.538309,
            0.582847,
            0.524758,
            0.546234
          ]
        },
        "v_measure": 0.529139,
        "v_measure_std": 0.030324,
        "main_score": 0.529139,
        "hf_subset": "kan_Knda",
        "languages": [
          "kan-Knda"
        ]
      },
      {
        "v_measures": {
          "Level 0": [
            0.4177,
            0.378811,
            0.341397,
            0.417498,
            0.420968,
            0.429607,
            0.337539,
            0.385783,
            0.419091,
            0.392497
          ]
        },
        "v_measure": 0.394089,
        "v_measure_std": 0.031613,
        "main_score": 0.394089,
        "hf_subset": "kas_Deva",
        "languages": [
          "kas-Deva"
        ]
      },
      {
        "v_measures": {
          "Level 0": [
            0.458966,
            0.485059,
            0.642187,
            0.458217,
            0.543944,
            0.498692,
            0.554225,
            0.526669,
            0.568621,
            0.55853
          ]
        },
        "v_measure": 0.529511,
        "v_measure_std": 0.05374,
        "main_score": 0.529511,
        "hf_subset": "kat_Geor",
        "languages": [
          "kat-Geor"
        ]
      },
      {
        "v_measures": {
          "Level 0": [
            0.518711,
            0.476047,
            0.538815,
            0.580809,
            0.501377,
            0.60774,
            0.580261,
            0.576911,
            0.584098,
            0.560294
          ]
        },
        "v_measure": 0.552506,
        "v_measure_std": 0.040083,
        "main_score": 0.552506,
        "hf_subset": "kaz_Cyrl",
        "languages": [
          "kaz-Cyrl"
        ]
      },
      {
        "v_measures": {
          "Level 0": [
            0.238385,
            0.25251,
            0.259917,
            0.196697,
            0.255165,
            0.210082,
            0.240723,
            0.257939,
            0.277919,
            0.236942
          ]
        },
        "v_measure": 0.242628,
        "v_measure_std": 0.022927,
        "main_score": 0.242628,
        "hf_subset": "kbp_Latn",
        "languages": [
          "kbp-Latn"
        ]
      },
      {
        "v_measures": {
          "Level 0": [
            0.527399,
            0.542014,
            0.392968,
            0.521535,
            0.526435,
            0.452297,
            0.478157,
            0.485654,
            0.45568,
            0.47676
          ]
        },
        "v_measure": 0.48589,
        "v_measure_std": 0.043135,
        "main_score": 0.48589,
        "hf_subset": "kea_Latn",
        "languages": [
          "kea-Latn"
        ]
      },
      {
        "v_measures": {
          "Level 0": [
            0.402616,
            0.424599,
            0.342028,
            0.451565,
            0.46433,
            0.44387,
            0.40209,
            0.488934,
            0.427985,
            0.420718
          ]
        },
        "v_measure": 0.426874,
        "v_measure_std": 0.038208,
        "main_score": 0.426874,
        "hf_subset": "khk_Cyrl",
        "languages": [
          "khk-Cyrl"
        ]
      },
      {
        "v_measures": {
          "Level 0": [
            0.510676,
            0.479908,
            0.433649,
            0.429029,
            0.43675,
            0.416694,
            0.509639,
            0.478879,
            0.445472,
            0.434844
          ]
        },
        "v_measure": 0.457554,
        "v_measure_std": 0.032617,
        "main_score": 0.457554,
        "hf_subset": "khm_Khmr",
        "languages": [
          "khm-Khmr"
        ]
      },
      {
        "v_measures": {
          "Level 0": [
            0.230445,
            0.254447,
            0.33029,
            0.288832,
            0.302822,
            0.291764,
            0.266548,
            0.264015,
            0.288275,
            0.289706
          ]
        },
        "v_measure": 0.280714,
        "v_measure_std": 0.026399,
        "main_score": 0.280714,
        "hf_subset": "kik_Latn",
        "languages": [
          "kik-Latn"
        ]
      },
      {
        "v_measures": {
          "Level 0": [
            0.402669,
            0.356234,
            0.312866,
            0.381599,
            0.369268,
            0.349593,
            0.376738,
            0.360458,
            0.341418,
            0.389949
          ]
        },
        "v_measure": 0.364079,
        "v_measure_std": 0.024644,
        "main_score": 0.364079,
        "hf_subset": "kin_Latn",
        "languages": [
          "kin-Latn"
        ]
      },
      {
        "v_measures": {
          "Level 0": [
            0.526324,
            0.556303,
            0.532896,
            0.526293,
            0.541247,
            0.553318,
            0.556141,
            0.55677,
            0.462637,
            0.526675
          ]
        },
        "v_measure": 0.53386,
        "v_measure_std": 0.026828,
        "main_score": 0.53386,
        "hf_subset": "kir_Cyrl",
        "languages": [
          "kir-Cyrl"
        ]
      },
      {
        "v_measures": {
          "Level 0": [
            0.216802,
            0.235935,
            0.202731,
            0.23375,
            0.151775,
            0.223802,
            0.200674,
            0.22862,
            0.223328,
            0.24571
          ]
        },
        "v_measure": 0.216313,
        "v_measure_std": 0.025307,
        "main_score": 0.216313,
        "hf_subset": "kmb_Latn",
        "languages": [
          "kmb-Latn"
        ]
      },
      {
        "v_measures": {
          "Level 0": [
            0.402002,
            0.333537,
            0.369229,
            0.335266,
            0.355956,
            0.381079,
            0.333768,
            0.377572,
            0.352272,
            0.372063
          ]
        },
        "v_measure": 0.361274,
        "v_measure_std": 0.021927,
        "main_score": 0.361274,
        "hf_subset": "kmr_Latn",
        "languages": [
          "kmr-Latn"
        ]
      },
      {
        "v_measures": {
          "Level 0": [
            0.298103,
            0.26139,
            0.316724,
            0.305716,
            0.250289,
            0.283483,
            0.313521,
            0.286015,
            0.260351,
            0.282989
          ]
        },
        "v_measure": 0.285858,
        "v_measure_std": 0.021887,
        "main_score": 0.285858,
        "hf_subset": "knc_Latn",
        "languages": [
          "knc-Latn"
        ]
      },
      {
        "v_measures": {
          "Level 0": [
            0.2971,
            0.308342,
            0.344403,
            0.314059,
            0.264693,
            0.344585,
            0.307933,
            0.341394,
            0.364179,
            0.338595
          ]
        },
        "v_measure": 0.322528,
        "v_measure_std": 0.027913,
        "main_score": 0.322528,
        "hf_subset": "kon_Latn",
        "languages": [
          "kon-Latn"
        ]
      },
      {
        "v_measures": {
          "Level 0": [
            0.538122,
            0.545013,
            0.539852,
            0.555223,
            0.552857,
            0.5348,
            0.521198,
            0.414785,
            0.492962,
            0.558345
          ]
        },
        "v_measure": 0.525316,
        "v_measure_std": 0.041083,
        "main_score": 0.525316,
        "hf_subset": "kor_Hang",
        "languages": [
          "kor-Hang"
        ]
      },
      {
        "v_measures": {
          "Level 0": [
            0.427853,
            0.416872,
            0.38872,
            0.38925,
            0.384738,
            0.398703,
            0.414737,
            0.33592,
            0.419439,
            0.416118
          ]
        },
        "v_measure": 0.399235,
        "v_measure_std": 0.025482,
        "main_score": 0.399235,
        "hf_subset": "lao_Laoo",
        "languages": [
          "lao-Laoo"
        ]
      },
      {
        "v_measures": {
          "Level 0": [
            0.475492,
            0.503028,
            0.359713,
            0.367798,
            0.391037,
            0.417086,
            0.49172,
            0.517217,
            0.44286,
            0.445357
          ]
        },
        "v_measure": 0.441131,
        "v_measure_std": 0.053362,
        "main_score": 0.441131,
        "hf_subset": "lij_Latn",
        "languages": [
          "lij-Latn"
        ]
      },
      {
        "v_measures": {
          "Level 0": [
            0.465082,
            0.48381,
            0.545305,
            0.45198,
            0.527524,
            0.558856,
            0.511738,
            0.531186,
            0.545214,
            0.534066
          ]
        },
        "v_measure": 0.515476,
        "v_measure_std": 0.034614,
        "main_score": 0.515476,
        "hf_subset": "lim_Latn",
        "languages": [
          "lim-Latn"
        ]
      },
      {
        "v_measures": {
          "Level 0": [
            0.257963,
            0.336525,
            0.322733,
            0.361183,
            0.291225,
            0.362604,
            0.303597,
            0.319658,
            0.328004,
            0.242798
          ]
        },
        "v_measure": 0.312629,
        "v_measure_std": 0.037707,
        "main_score": 0.312629,
        "hf_subset": "lin_Latn",
        "languages": [
          "lin-Latn"
        ]
      },
      {
        "v_measures": {
          "Level 0": [
            0.473799,
            0.424536,
            0.534235,
            0.488978,
            0.605236,
            0.49362,
            0.550733,
            0.578198,
            0.528799,
            0.479442
          ]
        },
        "v_measure": 0.515758,
        "v_measure_std": 0.051233,
        "main_score": 0.515758,
        "hf_subset": "lit_Latn",
        "languages": [
          "lit-Latn"
        ]
      },
      {
        "v_measures": {
          "Level 0": [
            0.510106,
            0.460847,
            0.508731,
            0.474684,
            0.492675,
            0.476171,
            0.505096,
            0.497493,
            0.452898,
            0.473454
          ]
        },
        "v_measure": 0.485215,
        "v_measure_std": 0.019348,
        "main_score": 0.485215,
        "hf_subset": "lmo_Latn",
        "languages": [
          "lmo-Latn"
        ]
      },
      {
        "v_measures": {
          "Level 0": [
            0.440631,
            0.408955,
            0.428702,
            0.418051,
            0.442929,
            0.391924,
            0.447916,
            0.431019,
            0.41583,
            0.451219
          ]
        },
        "v_measure": 0.427718,
        "v_measure_std": 0.017995,
        "main_score": 0.427718,
        "hf_subset": "ltg_Latn",
        "languages": [
          "ltg-Latn"
        ]
      },
      {
        "v_measures": {
          "Level 0": [
            0.553574,
            0.490019,
            0.572511,
            0.501662,
            0.595675,
            0.442318,
            0.521923,
            0.537361,
            0.5488,
            0.557579
          ]
        },
        "v_measure": 0.532142,
        "v_measure_std": 0.042372,
        "main_score": 0.532142,
        "hf_subset": "ltz_Latn",
        "languages": [
          "ltz-Latn"
        ]
      },
      {
        "v_measures": {
          "Level 0": [
            0.279872,
            0.325384,
            0.234799,
            0.300509,
            0.280914,
            0.291924,
            0.309024,
            0.326514,
            0.267512,
            0.303085
          ]
        },
        "v_measure": 0.291954,
        "v_measure_std": 0.026329,
        "main_score": 0.291954,
        "hf_subset": "lua_Latn",
        "languages": [
          "lua-Latn"
        ]
      },
      {
        "v_measures": {
          "Level 0": [
            0.244314,
            0.275317,
            0.220319,
            0.25086,
            0.294024,
            0.26474,
            0.195598,
            0.280853,
            0.229441,
            0.204135
          ]
        },
        "v_measure": 0.24596,
        "v_measure_std": 0.031599,
        "main_score": 0.24596,
        "hf_subset": "lug_Latn",
        "languages": [
          "lug-Latn"
        ]
      },
      {
        "v_measures": {
          "Level 0": [
            0.215234,
            0.212615,
            0.250464,
            0.295534,
            0.251194,
            0.222358,
            0.218184,
            0.25654,
            0.241514,
            0.215734
          ]
        },
        "v_measure": 0.237937,
        "v_measure_std": 0.025083,
        "main_score": 0.237937,
        "hf_subset": "luo_Latn",
        "languages": [
          "luo-Latn"
        ]
      },
      {
        "v_measures": {
          "Level 0": [
            0.422466,
            0.433467,
            0.464399,
            0.426382,
            0.42298,
            0.401739,
            0.395705,
            0.417477,
            0.337114,
            0.44213
          ]
        },
        "v_measure": 0.416386,
        "v_measure_std": 0.032199,
        "main_score": 0.416386,
        "hf_subset": "lus_Latn",
        "languages": [
          "lus-Latn"
        ]
      },
      {
        "v_measures": {
          "Level 0": [
            0.502286,
            0.541774,
            0.603233,
            0.504026,
            0.524873,
            0.519351,
            0.534525,
            0.522758,
            0.5111,
            0.494794
          ]
        },
        "v_measure": 0.525872,
        "v_measure_std": 0.029297,
        "main_score": 0.525872,
        "hf_subset": "lvs_Latn",
        "languages": [
          "lvs-Latn"
        ]
      },
      {
        "v_measures": {
          "Level 0": [
            0.489951,
            0.431087,
            0.519206,
            0.481463,
            0.550202,
            0.521915,
            0.454353,
            0.46691,
            0.489494,
            0.506271
          ]
        },
        "v_measure": 0.491085,
        "v_measure_std": 0.033312,
        "main_score": 0.491085,
        "hf_subset": "mag_Deva",
        "languages": [
          "mag-Deva"
        ]
      },
      {
        "v_measures": {
          "Level 0": [
            0.423007,
            0.509303,
            0.511896,
            0.606991,
            0.526451,
            0.456855,
            0.525814,
            0.558862,
            0.541077,
            0.550431
          ]
        },
        "v_measure": 0.521069,
        "v_measure_std": 0.049079,
        "main_score": 0.521069,
        "hf_subset": "mai_Deva",
        "languages": [
          "mai-Deva"
        ]
      },
      {
        "v_measures": {
          "Level 0": [
            0.54457,
            0.529014,
            0.429376,
            0.579493,
            0.54468,
            0.536408,
            0.487626,
            0.591094,
            0.555282,
            0.522721
          ]
        },
        "v_measure": 0.532026,
        "v_measure_std": 0.043845,
        "main_score": 0.532026,
        "hf_subset": "mal_Mlym",
        "languages": [
          "mal-Mlym"
        ]
      },
      {
        "v_measures": {
          "Level 0": [
            0.508782,
            0.52699,
            0.461647,
            0.547589,
            0.581112,
            0.533997,
            0.458058,
            0.601895,
            0.564267,
            0.541815
          ]
        },
        "v_measure": 0.532615,
        "v_measure_std": 0.044339,
        "main_score": 0.532615,
        "hf_subset": "mar_Deva",
        "languages": [
          "mar-Deva"
        ]
      },
      {
        "v_measures": {
          "Level 0": [
            0.451218,
            0.455988,
            0.443029,
            0.504413,
            0.506985,
            0.518794,
            0.436707,
            0.496734,
            0.440746,
            0.481176
          ]
        },
        "v_measure": 0.473579,
        "v_measure_std": 0.029808,
        "main_score": 0.473579,
        "hf_subset": "min_Latn",
        "languages": [
          "min-Latn"
        ]
      },
      {
        "v_measures": {
          "Level 0": [
            0.595212,
            0.507243,
            0.584544,
            0.528247,
            0.56618,
            0.54423,
            0.543729,
            0.578778,
            0.532887,
            0.544328
          ]
        },
        "v_measure": 0.552538,
        "v_measure_std": 0.026385,
        "main_score": 0.552538,
        "hf_subset": "mkd_Cyrl",
        "languages": [
          "mkd-Cyrl"
        ]
      },
      {
        "v_measures": {
          "Level 0": [
            0.497835,
            0.501286,
            0.509022,
            0.512899,
            0.542215,
            0.535593,
            0.46188,
            0.508772,
            0.507436,
            0.554358
          ]
        },
        "v_measure": 0.51313,
        "v_measure_std": 0.024737,
        "main_score": 0.51313,
        "hf_subset": "mlt_Latn",
        "languages": [
          "mlt-Latn"
        ]
      },
      {
        "v_measures": {
          "Level 0": [
            0.30166,
            0.317283,
            0.312852,
            0.269543,
            0.311726,
            0.293435,
            0.289201,
            0.28904,
            0.296763,
            0.316275
          ]
        },
        "v_measure": 0.299778,
        "v_measure_std": 0.014445,
        "main_score": 0.299778,
        "hf_subset": "mni_Beng",
        "languages": [
          "mni-Beng"
        ]
      },
      {
        "v_measures": {
          "Level 0": [
            0.225855,
            0.275074,
            0.249265,
            0.271982,
            0.230086,
            0.22988,
            0.21738,
            0.244228,
            0.239751,
            0.206274
          ]
        },
        "v_measure": 0.238978,
        "v_measure_std": 0.020967,
        "main_score": 0.238978,
        "hf_subset": "mos_Latn",
        "languages": [
          "mos-Latn"
        ]
      },
      {
        "v_measures": {
          "Level 0": [
            0.312042,
            0.309685,
            0.322296,
            0.433926,
            0.340469,
            0.322428,
            0.323568,
            0.31846,
            0.279364,
            0.346931
          ]
        },
        "v_measure": 0.330917,
        "v_measure_std": 0.038443,
        "main_score": 0.330917,
        "hf_subset": "mri_Latn",
        "languages": [
          "mri-Latn"
        ]
      },
      {
        "v_measures": {
          "Level 0": [
            0.468574,
            0.43461,
            0.475402,
            0.475794,
            0.518459,
            0.488088,
            0.494006,
            0.483272,
            0.449449,
            0.474381
          ]
        },
        "v_measure": 0.476203,
        "v_measure_std": 0.021913,
        "main_score": 0.476203,
        "hf_subset": "mya_Mymr",
        "languages": [
          "mya-Mymr"
        ]
      },
      {
        "v_measures": {
          "Level 0": [
            0.51393,
            0.498092,
            0.583246,
            0.527647,
            0.554877,
            0.484275,
            0.538719,
            0.557851,
            0.557116,
            0.516289
          ]
        },
        "v_measure": 0.533204,
        "v_measure_std": 0.029153,
        "main_score": 0.533204,
        "hf_subset": "nld_Latn",
        "languages": [
          "nld-Latn"
        ]
      },
      {
        "v_measures": {
          "Level 0": [
            0.561828,
            0.581024,
            0.502965,
            0.56995,
            0.564987,
            0.512388,
            0.473163,
            0.510068,
            0.497831,
            0.534629
          ]
        },
        "v_measure": 0.530883,
        "v_measure_std": 0.034863,
        "main_score": 0.530883,
        "hf_subset": "nno_Latn",
        "languages": [
          "nno-Latn"
        ]
      },
      {
        "v_measures": {
          "Level 0": [
            0.509382,
            0.564594,
            0.468676,
            0.49496,
            0.511267,
            0.571895,
            0.548593,
            0.583021,
            0.525362,
            0.52487
          ]
        },
        "v_measure": 0.530262,
        "v_measure_std": 0.034526,
        "main_score": 0.530262,
        "hf_subset": "nob_Latn",
        "languages": [
          "nob-Latn"
        ]
      },
      {
        "v_measures": {
          "Level 0": [
            0.507289,
            0.50442,
            0.546261,
            0.479903,
            0.481843,
            0.481361,
            0.478128,
            0.556673,
            0.548886,
            0.479474
          ]
        },
        "v_measure": 0.506424,
        "v_measure_std": 0.030631,
        "main_score": 0.506424,
        "hf_subset": "npi_Deva",
        "languages": [
          "npi-Deva"
        ]
      },
      {
        "v_measures": {
          "Level 0": [
            0.090869,
            0.09335,
            0.115222,
            0.089929,
            0.127129,
            0.095798,
            0.087079,
            0.109691,
            0.130246,
            0.112949
          ]
        },
        "v_measure": 0.105226,
        "v_measure_std": 0.015115,
        "main_score": 0.105226,
        "hf_subset": "nqo_Nkoo",
        "languages": [
          "nqo-Nkoo"
        ]
      },
      {
        "v_measures": {
          "Level 0": [
            0.247163,
            0.321904,
            0.29071,
            0.281603,
            0.322786,
            0.290879,
            0.311415,
            0.315027,
            0.29245,
            0.33621
          ]
        },
        "v_measure": 0.301015,
        "v_measure_std": 0.024521,
        "main_score": 0.301015,
        "hf_subset": "nso_Latn",
        "languages": [
          "nso-Latn"
        ]
      },
      {
        "v_measures": {
          "Level 0": [
            0.158352,
            0.161477,
            0.162777,
            0.119426,
            0.178338,
            0.116912,
            0.1742,
            0.176491,
            0.138155,
            0.186823
          ]
        },
        "v_measure": 0.157295,
        "v_measure_std": 0.023343,
        "main_score": 0.157295,
        "hf_subset": "nus_Latn",
        "languages": [
          "nus-Latn"
        ]
      },
      {
        "v_measures": {
          "Level 0": [
            0.338371,
            0.422621,
            0.337397,
            0.340439,
            0.392255,
            0.381779,
            0.333195,
            0.366861,
            0.303941,
            0.322625
          ]
        },
        "v_measure": 0.353949,
        "v_measure_std": 0.034258,
        "main_score": 0.353949,
        "hf_subset": "nya_Latn",
        "languages": [
          "nya-Latn"
        ]
      },
      {
        "v_measures": {
          "Level 0": [
            0.526061,
            0.524206,
            0.485001,
            0.50407,
            0.46016,
            0.519286,
            0.473336,
            0.474819,
            0.563078,
            0.574462
          ]
        },
        "v_measure": 0.510448,
        "v_measure_std": 0.036391,
        "main_score": 0.510448,
        "hf_subset": "oci_Latn",
        "languages": [
          "oci-Latn"
        ]
      },
      {
        "v_measures": {
          "Level 0": [
            0.498191,
            0.481111,
            0.473704,
            0.497241,
            0.508355,
            0.515464,
            0.556762,
            0.503055,
            0.495566,
            0.427113
          ]
        },
        "v_measure": 0.495656,
        "v_measure_std": 0.031214,
        "main_score": 0.495656,
        "hf_subset": "ory_Orya",
        "languages": [
          "ory-Orya"
        ]
      },
      {
        "v_measures": {
          "Level 0": [
            0.435744,
            0.460599,
            0.48225,
            0.483232,
            0.468592,
            0.477646,
            0.403676,
            0.488527,
            0.470304,
            0.430838
          ]
        },
        "v_measure": 0.460141,
        "v_measure_std": 0.026365,
        "main_score": 0.460141,
        "hf_subset": "pag_Latn",
        "languages": [
          "pag-Latn"
        ]
      },
      {
        "v_measures": {
          "Level 0": [
            0.527776,
            0.531949,
            0.496563,
            0.514703,
            0.529199,
            0.488129,
            0.509487,
            0.517961,
            0.5532,
            0.534846
          ]
        },
        "v_measure": 0.520381,
        "v_measure_std": 0.018212,
        "main_score": 0.520381,
        "hf_subset": "pan_Guru",
        "languages": [
          "pan-Guru"
        ]
      },
      {
        "v_measures": {
          "Level 0": [
            0.569832,
            0.509816,
            0.541829,
            0.470416,
            0.516005,
            0.435724,
            0.497518,
            0.508707,
            0.480733,
            0.565947
          ]
        },
        "v_measure": 0.509653,
        "v_measure_std": 0.039819,
        "main_score": 0.509653,
        "hf_subset": "pap_Latn",
        "languages": [
          "pap-Latn"
        ]
      },
      {
        "v_measures": {
          "Level 0": [
            0.442407,
            0.439394,
            0.484019,
            0.409547,
            0.414131,
            0.48731,
            0.418593,
            0.484637,
            0.440099,
            0.4584
          ]
        },
        "v_measure": 0.447854,
        "v_measure_std": 0.028198,
        "main_score": 0.447854,
        "hf_subset": "pbt_Arab",
        "languages": [
          "pbt-Arab"
        ]
      },
      {
        "v_measures": {
          "Level 0": [
            0.57624,
            0.582348,
            0.422463,
            0.577929,
            0.52923,
            0.597058,
            0.501143,
            0.600807,
            0.496162,
            0.602524
          ]
        },
        "v_measure": 0.54859,
        "v_measure_std": 0.056597,
        "main_score": 0.54859,
        "hf_subset": "pes_Arab",
        "languages": [
          "pes-Arab"
        ]
      },
      {
        "v_measures": {
          "Level 0": [
            0.357565,
            0.371515,
            0.351528,
            0.361274,
            0.325975,
            0.359089,
            0.382747,
            0.407978,
            0.337071,
            0.419691
          ]
        },
        "v_measure": 0.367443,
        "v_measure_std": 0.027793,
        "main_score": 0.367443,
        "hf_subset": "plt_Latn",
        "languages": [
          "plt-Latn"
        ]
      },
      {
        "v_measures": {
          "Level 0": [
            0.573229,
            0.476054,
            0.543417,
            0.558133,
            0.535243,
            0.551715,
            0.578868,
            0.486524,
            0.547921,
            0.49842
          ]
        },
        "v_measure": 0.534952,
        "v_measure_std": 0.03406,
        "main_score": 0.534952,
        "hf_subset": "pol_Latn",
        "languages": [
          "pol-Latn"
        ]
      },
      {
        "v_measures": {
          "Level 0": [
            0.508969,
            0.470752,
            0.610142,
            0.577093,
            0.550191,
            0.563179,
            0.496594,
            0.57566,
            0.61555,
            0.488992
          ]
        },
        "v_measure": 0.545712,
        "v_measure_std": 0.04882,
        "main_score": 0.545712,
        "hf_subset": "por_Latn",
        "languages": [
          "por-Latn"
        ]
      },
      {
        "v_measures": {
          "Level 0": [
            0.501728,
            0.548606,
            0.543761,
            0.544689,
            0.495388,
            0.434363,
            0.525956,
            0.473599,
            0.57189,
            0.500286
          ]
        },
        "v_measure": 0.514026,
        "v_measure_std": 0.03896,
        "main_score": 0.514026,
        "hf_subset": "prs_Arab",
        "languages": [
          "prs-Arab"
        ]
      },
      {
        "v_measures": {
          "Level 0": [
            0.279767,
            0.349689,
            0.307572,
            0.259466,
            0.215672,
            0.319094,
            0.316001,
            0.258557,
            0.296148,
            0.260224
          ]
        },
        "v_measure": 0.286219,
        "v_measure_std": 0.037048,
        "main_score": 0.286219,
        "hf_subset": "quy_Latn",
        "languages": [
          "quy-Latn"
        ]
      },
      {
        "v_measures": {
          "Level 0": [
            0.547828,
            0.541715,
            0.621924,
            0.510396,
            0.60703,
            0.460983,
            0.566374,
            0.631784,
            0.579072,
            0.544319
          ]
        },
        "v_measure": 0.561143,
        "v_measure_std": 0.049582,
        "main_score": 0.561143,
        "hf_subset": "ron_Latn",
        "languages": [
          "ron-Latn"
        ]
      },
      {
        "v_measures": {
          "Level 0": [
            0.313223,
            0.294383,
            0.28234,
            0.307339,
            0.309533,
            0.324819,
            0.336229,
            0.333647,
            0.311684,
            0.261362
          ]
        },
        "v_measure": 0.307456,
        "v_measure_std": 0.021902,
        "main_score": 0.307456,
        "hf_subset": "run_Latn",
        "languages": [
          "run-Latn"
        ]
      },
      {
        "v_measures": {
          "Level 0": [
            0.52759,
            0.551244,
            0.559152,
            0.598981,
            0.582672,
            0.568617,
            0.485157,
            0.472798,
            0.584846,
            0.592132
          ]
        },
        "v_measure": 0.552319,
        "v_measure_std": 0.041834,
        "main_score": 0.552319,
        "hf_subset": "rus_Cyrl",
        "languages": [
          "rus-Cyrl"
        ]
      },
      {
        "v_measures": {
          "Level 0": [
            0.235819,
            0.237345,
            0.204245,
            0.216268,
            0.275928,
            0.282157,
            0.23471,
            0.249046,
            0.278257,
            0.228957
          ]
        },
        "v_measure": 0.244273,
        "v_measure_std": 0.025391,
        "main_score": 0.244273,
        "hf_subset": "sag_Latn",
        "languages": [
          "sag-Latn"
        ]
      },
      {
        "v_measures": {
          "Level 0": [
            0.472595,
            0.418736,
            0.48425,
            0.411538,
            0.505125,
            0.474563,
            0.464904,
            0.402441,
            0.422197,
            0.472538
          ]
        },
        "v_measure": 0.452889,
        "v_measure_std": 0.033859,
        "main_score": 0.452889,
        "hf_subset": "san_Deva",
        "languages": [
          "san-Deva"
        ]
      },
      {
        "v_measures": {
          "Level 0": [
            0.321629,
            0.415904,
            0.416993,
            0.313869,
            0.376989,
            0.404625,
            0.330563,
            0.400164,
            0.44635,
            0.417793
          ]
        },
        "v_measure": 0.384488,
        "v_measure_std": 0.044197,
        "main_score": 0.384488,
        "hf_subset": "sat_Olck",
        "languages": [
          "sat-Olck"
        ]
      },
      {
        "v_measures": {
          "Level 0": [
            0.528716,
            0.558359,
            0.543982,
            0.541726,
            0.441315,
            0.511492,
            0.456079,
            0.496636,
            0.53863,
            0.55027
          ]
        },
        "v_measure": 0.516721,
        "v_measure_std": 0.03827,
        "main_score": 0.516721,
        "hf_subset": "scn_Latn",
        "languages": [
          "scn-Latn"
        ]
      },
      {
        "v_measures": {
          "Level 0": [
            0.250278,
            0.229131,
            0.245531,
            0.26316,
            0.266006,
            0.229374,
            0.207813,
            0.251277,
            0.235666,
            0.259447
          ]
        },
        "v_measure": 0.243768,
        "v_measure_std": 0.017315,
        "main_score": 0.243768,
        "hf_subset": "shn_Mymr",
        "languages": [
          "shn-Mymr"
        ]
      },
      {
        "v_measures": {
          "Level 0": [
            0.524604,
            0.537883,
            0.487941,
            0.476324,
            0.501169,
            0.465453,
            0.513103,
            0.571735,
            0.474279,
            0.500298
          ]
        },
        "v_measure": 0.505279,
        "v_measure_std": 0.031052,
        "main_score": 0.505279,
        "hf_subset": "sin_Sinh",
        "languages": [
          "sin-Sinh"
        ]
      },
      {
        "v_measures": {
          "Level 0": [
            0.451661,
            0.529627,
            0.541612,
            0.578821,
            0.594397,
            0.515677,
            0.541624,
            0.464451,
            0.519007,
            0.586673
          ]
        },
        "v_measure": 0.532355,
        "v_measure_std": 0.045515,
        "main_score": 0.532355,
        "hf_subset": "slk_Latn",
        "languages": [
          "slk-Latn"
        ]
      },
      {
        "v_measures": {
          "Level 0": [
            0.526244,
            0.475154,
            0.529479,
            0.494614,
            0.581636,
            0.506017,
            0.531942,
            0.51452,
            0.572233,
            0.48218
          ]
        },
        "v_measure": 0.521402,
        "v_measure_std": 0.033302,
        "main_score": 0.521402,
        "hf_subset": "slv_Latn",
        "languages": [
          "slv-Latn"
        ]
      },
      {
        "v_measures": {
          "Level 0": [
            0.295043,
            0.264284,
            0.322162,
            0.345373,
            0.341494,
            0.300885,
            0.296002,
            0.319117,
            0.315766,
            0.326163
          ]
        },
        "v_measure": 0.312629,
        "v_measure_std": 0.023005,
        "main_score": 0.312629,
        "hf_subset": "smo_Latn",
        "languages": [
          "smo-Latn"
        ]
      },
      {
        "v_measures": {
          "Level 0": [
            0.320898,
            0.380767,
            0.398751,
            0.40678,
            0.373036,
            0.329536,
            0.396502,
            0.326428,
            0.296828,
            0.41439
          ]
        },
        "v_measure": 0.364392,
        "v_measure_std": 0.039955,
        "main_score": 0.364392,
        "hf_subset": "sna_Latn",
        "languages": [
          "sna-Latn"
        ]
      },
      {
        "v_measures": {
          "Level 0": [
            0.513999,
            0.422415,
            0.504443,
            0.4904,
            0.463646,
            0.499707,
            0.460954,
            0.469889,
            0.488589,
            0.456129
          ]
        },
        "v_measure": 0.477017,
        "v_measure_std": 0.026178,
        "main_score": 0.477017,
        "hf_subset": "snd_Arab",
        "languages": [
          "snd-Arab"
        ]
      },
      {
        "v_measures": {
          "Level 0": [
            0.416764,
            0.358711,
            0.339786,
            0.353454,
            0.393625,
            0.357893,
            0.431067,
            0.356643,
            0.362241,
            0.422612
          ]
        },
        "v_measure": 0.37928,
        "v_measure_std": 0.03175,
        "main_score": 0.37928,
        "hf_subset": "som_Latn",
        "languages": [
          "som-Latn"
        ]
      },
      {
        "v_measures": {
          "Level 0": [
            0.341072,
            0.360744,
            0.301616,
            0.338152,
            0.334014,
            0.329758,
            0.33543,
            0.362275,
            0.354703,
            0.34282
          ]
        },
        "v_measure": 0.340058,
        "v_measure_std": 0.016704,
        "main_score": 0.340058,
        "hf_subset": "sot_Latn",
        "languages": [
          "sot-Latn"
        ]
      },
      {
        "v_measures": {
          "Level 0": [
            0.510278,
            0.530155,
            0.431177,
            0.462453,
            0.471564,
            0.515985,
            0.464356,
            0.573652,
            0.530153,
            0.529564
          ]
        },
        "v_measure": 0.501934,
        "v_measure_std": 0.040824,
        "main_score": 0.501934,
        "hf_subset": "spa_Latn",
        "languages": [
          "spa-Latn"
        ]
      },
      {
        "v_measures": {
          "Level 0": [
            0.463953,
            0.490229,
            0.510416,
            0.552838,
            0.496939,
            0.442477,
            0.459988,
            0.456912,
            0.513172,
            0.546096
          ]
        },
        "v_measure": 0.493302,
        "v_measure_std": 0.035945,
        "main_score": 0.493302,
        "hf_subset": "srd_Latn",
        "languages": [
          "srd-Latn"
        ]
      },
      {
        "v_measures": {
          "Level 0": [
            0.62484,
            0.518439,
            0.519762,
            0.539092,
            0.578821,
            0.47352,
            0.585611,
            0.574697,
            0.530012,
            0.583849
          ]
        },
        "v_measure": 0.552864,
        "v_measure_std": 0.042014,
        "main_score": 0.552864,
        "hf_subset": "srp_Cyrl",
        "languages": [
          "srp-Cyrl"
        ]
      },
      {
        "v_measures": {
          "Level 0": [
            0.31022,
            0.334515,
            0.292996,
            0.333472,
            0.351396,
            0.370204,
            0.321164,
            0.254446,
            0.367874,
            0.305116
          ]
        },
        "v_measure": 0.32414,
        "v_measure_std": 0.03371,
        "main_score": 0.32414,
        "hf_subset": "ssw_Latn",
        "languages": [
          "ssw-Latn"
        ]
      },
      {
        "v_measures": {
          "Level 0": [
            0.552085,
            0.544054,
            0.57282,
            0.561098,
            0.513111,
            0.538579,
            0.512679,
            0.570195,
            0.434274,
            0.511884
          ]
        },
        "v_measure": 0.531078,
        "v_measure_std": 0.039039,
        "main_score": 0.531078,
        "hf_subset": "sun_Latn",
        "languages": [
          "sun-Latn"
        ]
      },
      {
        "v_measures": {
          "Level 0": [
            0.544437,
            0.48604,
            0.59189,
            0.485717,
            0.505642,
            0.542523,
            0.49468,
            0.576859,
            0.497637,
            0.559062
          ]
        },
        "v_measure": 0.528449,
        "v_measure_std": 0.037408,
        "main_score": 0.528449,
        "hf_subset": "swe_Latn",
        "languages": [
          "swe-Latn"
        ]
      },
      {
        "v_measures": {
          "Level 0": [
            0.54201,
            0.505624,
            0.530932,
            0.53084,
            0.573368,
            0.508453,
            0.528742,
            0.496469,
            0.526776,
            0.542935
          ]
        },
        "v_measure": 0.528615,
        "v_measure_std": 0.020903,
        "main_score": 0.528615,
        "hf_subset": "swh_Latn",
        "languages": [
          "swh-Latn"
        ]
      },
      {
        "v_measures": {
          "Level 0": [
            0.43439,
            0.542562,
            0.435113,
            0.465211,
            0.491503,
            0.522337,
            0.489468,
            0.501724,
            0.437904,
            0.450211
          ]
        },
        "v_measure": 0.477042,
        "v_measure_std": 0.03645,
        "main_score": 0.477042,
        "hf_subset": "szl_Latn",
        "languages": [
          "szl-Latn"
        ]
      },
      {
        "v_measures": {
          "Level 0": [
            0.539116,
            0.553034,
            0.547724,
            0.535708,
            0.540092,
            0.536908,
            0.53605,
            0.518449,
            0.556134,
            0.542883
          ]
        },
        "v_measure": 0.54061,
        "v_measure_std": 0.010016,
        "main_score": 0.54061,
        "hf_subset": "tam_Taml",
        "languages": [
          "tam-Taml"
        ]
      },
      {
        "v_measures": {
          "Level 0": [
            0.044781,
            0.051319,
            0.050455,
            0.050885,
            0.059467,
            0.047177,
            0.062672,
            0.050939,
            0.042686,
            0.051274
          ]
        },
        "v_measure": 0.051165,
        "v_measure_std": 0.005749,
        "main_score": 0.051165,
        "hf_subset": "taq_Tfng",
        "languages": [
          "taq-Tfng"
        ]
      },
      {
        "v_measures": {
          "Level 0": [
            0.550643,
            0.551808,
            0.529455,
            0.48545,
            0.508623,
            0.476034,
            0.529844,
            0.565185,
            0.454746,
            0.486888
          ]
        },
        "v_measure": 0.513868,
        "v_measure_std": 0.035232,
        "main_score": 0.513868,
        "hf_subset": "tat_Cyrl",
        "languages": [
          "tat-Cyrl"
        ]
      },
      {
        "v_measures": {
          "Level 0": [
            0.502234,
            0.554885,
            0.426005,
            0.456681,
            0.569992,
            0.505325,
            0.501654,
            0.472333,
            0.541174,
            0.546528
          ]
        },
        "v_measure": 0.507681,
        "v_measure_std": 0.043971,
        "main_score": 0.507681,
        "hf_subset": "tel_Telu",
        "languages": [
          "tel-Telu"
        ]
      },
      {
        "v_measures": {
          "Level 0": [
            0.501367,
            0.523492,
            0.497325,
            0.474285,
            0.469824,
            0.472982,
            0.461114,
            0.475725,
            0.500125,
            0.434986
          ]
        },
        "v_measure": 0.481123,
        "v_measure_std": 0.023722,
        "main_score": 0.481123,
        "hf_subset": "tgk_Cyrl",
        "languages": [
          "tgk-Cyrl"
        ]
      },
      {
        "v_measures": {
          "Level 0": [
            0.524678,
            0.571378,
            0.455306,
            0.511965,
            0.568667,
            0.553313,
            0.500401,
            0.61823,
            0.558699,
            0.510051
          ]
        },
        "v_measure": 0.537269,
        "v_measure_std": 0.043632,
        "main_score": 0.537269,
        "hf_subset": "tgl_Latn",
        "languages": [
          "tgl-Latn"
        ]
      },
      {
        "v_measures": {
          "Level 0": [
            0.541433,
            0.524953,
            0.530926,
            0.561251,
            0.527277,
            0.54201,
            0.571209,
            0.523079,
            0.501886,
            0.487741
          ]
        },
        "v_measure": 0.531176,
        "v_measure_std": 0.023651,
        "main_score": 0.531176,
        "hf_subset": "tha_Thai",
        "languages": [
          "tha-Thai"
        ]
      },
      {
        "v_measures": {
          "Level 0": [
            0.314132,
            0.288857,
            0.310151,
            0.236294,
            0.301111,
            0.295956,
            0.300526,
            0.267931,
            0.296316,
            0.246132
          ]
        },
        "v_measure": 0.285741,
        "v_measure_std": 0.025325,
        "main_score": 0.285741,
        "hf_subset": "tir_Ethi",
        "languages": [
          "tir-Ethi"
        ]
      },
      {
        "v_measures": {
          "Level 0": [
            0.524484,
            0.512156,
            0.499652,
            0.497953,
            0.526699,
            0.549167,
            0.515256,
            0.542769,
            0.525409,
            0.554464
          ]
        },
        "v_measure": 0.524801,
        "v_measure_std": 0.018452,
        "main_score": 0.524801,
        "hf_subset": "tpi_Latn",
        "languages": [
          "tpi-Latn"
        ]
      },
      {
        "v_measures": {
          "Level 0": [
            0.27635,
            0.25992,
            0.271055,
            0.338673,
            0.307156,
            0.310234,
            0.236067,
            0.281031,
            0.272565,
            0.294671
          ]
        },
        "v_measure": 0.284772,
        "v_measure_std": 0.027504,
        "main_score": 0.284772,
        "hf_subset": "tsn_Latn",
        "languages": [
          "tsn-Latn"
        ]
      },
      {
        "v_measures": {
          "Level 0": [
            0.287866,
            0.255632,
            0.218761,
            0.217541,
            0.335422,
            0.254075,
            0.269024,
            0.26546,
            0.281984,
            0.270919
          ]
        },
        "v_measure": 0.265669,
        "v_measure_std": 0.032272,
        "main_score": 0.265669,
        "hf_subset": "tso_Latn",
        "languages": [
          "tso-Latn"
        ]
      },
      {
        "v_measures": {
          "Level 0": [
            0.527544,
            0.457698,
            0.520633,
            0.510137,
            0.473404,
            0.496654,
            0.552322,
            0.45975,
            0.544713,
            0.532103
          ]
        },
        "v_measure": 0.507496,
        "v_measure_std": 0.03259,
        "main_score": 0.507496,
        "hf_subset": "tuk_Latn",
        "languages": [
          "tuk-Latn"
        ]
      },
      {
        "v_measures": {
          "Level 0": [
            0.339243,
            0.305877,
            0.34146,
            0.362027,
            0.339498,
            0.348737,
            0.326736,
            0.332108,
            0.360082,
            0.314512
          ]
        },
        "v_measure": 0.337028,
        "v_measure_std": 0.017122,
        "main_score": 0.337028,
        "hf_subset": "tum_Latn",
        "languages": [
          "tum-Latn"
        ]
      },
      {
        "v_measures": {
          "Level 0": [
            0.529887,
            0.563361,
            0.504012,
            0.471379,
            0.584825,
            0.593515,
            0.58958,
            0.587113,
            0.49044,
            0.565778
          ]
        },
        "v_measure": 0.547989,
        "v_measure_std": 0.043227,
        "main_score": 0.547989,
        "hf_subset": "tur_Latn",
        "languages": [
          "tur-Latn"
        ]
      },
      {
        "v_measures": {
          "Level 0": [
            0.352138,
            0.28136,
            0.320998,
            0.317304,
            0.377803,
            0.365736,
            0.372408,
            0.290395,
            0.317679,
            0.344098
          ]
        },
        "v_measure": 0.333992,
        "v_measure_std": 0.031967,
        "main_score": 0.333992,
        "hf_subset": "twi_Latn",
        "languages": [
          "twi-Latn"
        ]
      },
      {
        "v_measures": {
          "Level 0": [
            0.037558,
            0.054964,
            0.04632,
            0.048278,
            0.058357,
            0.043023,
            0.047554,
            0.049865,
            0.046836,
            0.053024
          ]
        },
        "v_measure": 0.048578,
        "v_measure_std": 0.005651,
        "main_score": 0.048578,
        "hf_subset": "tzm_Tfng",
        "languages": [
          "tzm-Tfng"
        ]
      },
      {
        "v_measures": {
          "Level 0": [
            0.379966,
            0.338678,
            0.416878,
            0.339922,
            0.368291,
            0.328592,
            0.400709,
            0.38079,
            0.376974,
            0.41264
          ]
        },
        "v_measure": 0.374344,
        "v_measure_std": 0.02939,
        "main_score": 0.374344,
        "hf_subset": "uig_Arab",
        "languages": [
          "uig-Arab"
        ]
      },
      {
        "v_measures": {
          "Level 0": [
            0.59178,
            0.551737,
            0.540272,
            0.588219,
            0.518338,
            0.604897,
            0.496449,
            0.487336,
            0.541647,
            0.56992
          ]
        },
        "v_measure": 0.549059,
        "v_measure_std": 0.038174,
        "main_score": 0.549059,
        "hf_subset": "ukr_Cyrl",
        "languages": [
          "ukr-Cyrl"
        ]
      },
      {
        "v_measures": {
          "Level 0": [
            0.234806,
            0.211175,
            0.206724,
            0.243892,
            0.219775,
            0.236353,
            0.22775,
            0.220374,
            0.220454,
            0.229145
          ]
        },
        "v_measure": 0.225045,
        "v_measure_std": 0.01096,
        "main_score": 0.225045,
        "hf_subset": "umb_Latn",
        "languages": [
          "umb-Latn"
        ]
      },
      {
        "v_measures": {
          "Level 0": [
            0.490634,
            0.500786,
            0.535343,
            0.560209,
            0.561326,
            0.525016,
            0.502247,
            0.58124,
            0.556669,
            0.522212
          ]
        },
        "v_measure": 0.533568,
        "v_measure_std": 0.028967,
        "main_score": 0.533568,
        "hf_subset": "urd_Arab",
        "languages": [
          "urd-Arab"
        ]
      },
      {
        "v_measures": {
          "Level 0": [
            0.462201,
            0.588057,
            0.530927,
            0.499512,
            0.492891,
            0.537746,
            0.477357,
            0.494035,
            0.494158,
            0.522827
          ]
        },
        "v_measure": 0.509971,
        "v_measure_std": 0.03424,
        "main_score": 0.509971,
        "hf_subset": "uzn_Latn",
        "languages": [
          "uzn-Latn"
        ]
      },
      {
        "v_measures": {
          "Level 0": [
            0.551981,
            0.594134,
            0.499223,
            0.536858,
            0.494915,
            0.519611,
            0.543581,
            0.557128,
            0.542388,
            0.528082
          ]
        },
        "v_measure": 0.53679,
        "v_measure_std": 0.02747,
        "main_score": 0.53679,
        "hf_subset": "vec_Latn",
        "languages": [
          "vec-Latn"
        ]
      },
      {
        "v_measures": {
          "Level 0": [
            0.476913,
            0.53664,
            0.58163,
            0.573692,
            0.59431,
            0.585629,
            0.535885,
            0.492334,
            0.540903,
            0.613713
          ]
        },
        "v_measure": 0.553165,
        "v_measure_std": 0.042286,
        "main_score": 0.553165,
        "hf_subset": "vie_Latn",
        "languages": [
          "vie-Latn"
        ]
      },
      {
        "v_measures": {
          "Level 0": [
            0.493414,
            0.520599,
            0.578022,
            0.445555,
            0.476282,
            0.472006,
            0.515688,
            0.477747,
            0.443172,
            0.546547
          ]
        },
        "v_measure": 0.496903,
        "v_measure_std": 0.041118,
        "main_score": 0.496903,
        "hf_subset": "war_Latn",
        "languages": [
          "war-Latn"
        ]
      },
      {
        "v_measures": {
          "Level 0": [
            0.352247,
            0.342415,
            0.275916,
            0.34576,
            0.312918,
            0.351413,
            0.328499,
            0.313573,
            0.282373,
            0.375646
          ]
        },
        "v_measure": 0.328076,
        "v_measure_std": 0.030265,
        "main_score": 0.328076,
        "hf_subset": "wol_Latn",
        "languages": [
          "wol-Latn"
        ]
      },
      {
        "v_measures": {
          "Level 0": [
            0.391027,
            0.42006,
            0.359665,
            0.401325,
            0.403544,
            0.391705,
            0.414686,
            0.359466,
            0.436214,
            0.345557
          ]
        },
        "v_measure": 0.392325,
        "v_measure_std": 0.027817,
        "main_score": 0.392325,
        "hf_subset": "xho_Latn",
        "languages": [
          "xho-Latn"
        ]
      },
      {
        "v_measures": {
          "Level 0": [
            0.512984,
            0.428283,
            0.481499,
            0.51032,
            0.476184,
            0.522403,
            0.469011,
            0.482236,
            0.436494,
            0.480084
          ]
        },
        "v_measure": 0.47995,
        "v_measure_std": 0.029181,
        "main_score": 0.47995,
        "hf_subset": "ydd_Hebr",
        "languages": [
          "ydd-Hebr"
        ]
      },
      {
        "v_measures": {
          "Level 0": [
            0.253749,
            0.247075,
            0.223533,
            0.241405,
            0.211461,
            0.238143,
            0.232562,
            0.241745,
            0.25281,
            0.252869
          ]
        },
        "v_measure": 0.239535,
        "v_measure_std": 0.0131,
        "main_score": 0.239535,
        "hf_subset": "yor_Latn",
        "languages": [
          "yor-Latn"
        ]
      },
      {
        "v_measures": {
          "Level 0": [
            0.477219,
            0.551257,
            0.569143,
            0.559407,
            0.544646,
            0.491263,
            0.432509,
            0.519186,
            0.508426,
            0.6181
          ]
        },
        "v_measure": 0.527115,
        "v_measure_std": 0.050115,
        "main_score": 0.527115,
        "hf_subset": "yue_Hant",
        "languages": [
          "yue-Hant"
        ]
      },
      {
        "v_measures": {
          "Level 0": [
            0.566946,
            0.567217,
            0.548027,
            0.602799,
            0.510836,
            0.506414,
            0.602571,
            0.554359,
            0.577757,
            0.486569
          ]
        },
        "v_measure": 0.55235,
        "v_measure_std": 0.037855,
        "main_score": 0.55235,
        "hf_subset": "zho_Hant",
        "languages": [
          "zho-Hant"
        ]
      },
      {
        "v_measures": {
          "Level 0": [
            0.520181,
            0.50151,
            0.499521,
            0.524645,
            0.561342,
            0.505784,
            0.57129,
            0.53578,
            0.500177,
            0.544211
          ]
        },
        "v_measure": 0.526444,
        "v_measure_std": 0.024774,
        "main_score": 0.526444,
        "hf_subset": "zsm_Latn",
        "languages": [
          "zsm-Latn"
        ]
      },
      {
        "v_measures": {
          "Level 0": [
            0.342547,
            0.39431,
            0.362137,
            0.369396,
            0.453342,
            0.37822,
            0.394669,
            0.420598,
            0.405332,
            0.381788
          ]
        },
        "v_measure": 0.390234,
        "v_measure_std": 0.029803,
        "main_score": 0.390234,
        "hf_subset": "zul_Latn",
        "languages": [
          "zul-Latn"
        ]
      }
    ]
  },
  "evaluation_time": 2852.6583728790283,
  "kg_co2_emissions": null
}